shakeabuse/__init__.py
shakeabuse/__main__.py
shakeabuse/abuses.py
shakeabuse/insults_full.py
shakeabuse/insults_parts.py
shakeabuse/make_abuse.py
shakeabuse-1.0.2.dist-info/LICENSE
shakeabuse-1.0.2.dist-info/METADATA
shakeabuse-1.0.2.dist-info/WHEEL
shakeabuse-1.0.2.dist-info/entry_points.txt
shakeabuse-1.0.2.dist-info/top_level.txt
shakeabuse-1.0.2.dist-info/RECORD
